Release/_impl.cp310-win_amd64.exp
Release/_impl.cp310-win_amd64.lib
stt/__init__.py
stt/_impl.cp310-win_amd64.pyd
stt/client.py
stt/impl.py
stt/lib/libkenlm.so
stt/lib/libstt.so
iara_stt-1.6.2.dist-info/METADATA
iara_stt-1.6.2.dist-info/WHEEL
iara_stt-1.6.2.dist-info/entry_points.txt
iara_stt-1.6.2.dist-info/top_level.txt
iara_stt-1.6.2.dist-info/RECORD
